empiric/__init__.py
empiric/core/__init__.py
empiric/core/abis/__init__.py
empiric/core/abis/oracle.py
empiric/core/abis/proxy.py
empiric/core/abis/publisher_registry.py
empiric/core/abis/randomness.py
empiric/core/abis/summary_stats.py
empiric/core/client.py
empiric/core/config.py
empiric/core/contract.py
empiric/core/entry.py
empiric/core/logger.py
empiric/core/mixins/__init__.py
empiric/core/mixins/evm.py
empiric/core/mixins/nonce.py
empiric/core/mixins/oracle.py
empiric/core/mixins/publisher_registry.py
empiric/core/mixins/transactions.py
empiric/core/types.py
empiric/core/utils.py
empiric/publisher/__init__.py
empiric/publisher/assets.py
empiric/publisher/client.py
empiric/publisher/fetchers/__init__.py
empiric/publisher/fetchers/ascendex.py
empiric/publisher/fetchers/bitstamp.py
empiric/publisher/fetchers/cex.py
empiric/publisher/fetchers/coinbase.py
empiric/publisher/fetchers/coingecko.py
empiric/publisher/fetchers/defillama.py
empiric/publisher/fetchers/gecko.py
empiric/publisher/fetchers/gemini.py
empiric/publisher/fetchers/kaiko.py
empiric/publisher/fetchers/okx.py
empiric/publisher/fetchers/thegraph.py
empiric/publisher/future_fetchers/__init__.py
empiric/publisher/future_fetchers/binance.py
empiric/publisher/future_fetchers/bybit.py
empiric/publisher/future_fetchers/okx.py
empiric/publisher/future_fetchers/test.py
empiric/publisher/types.py
empiric/test/__init__.py
empiric/test/interface_consistency.py
empiric_network-1.8.8.dist-info/METADATA
empiric_network-1.8.8.dist-info/WHEEL
empiric_network-1.8.8.dist-info/entry_points.txt
empiric_network-1.8.8.dist-info/RECORD
