Metadata-Version: 2.1
Name: empiric-network
Version: 1.8.8
Summary: Core package for rollup-native Pragma Oracle
Home-page: https://pragmaoracle.com
Author: Pragma
Author-email: contact@pragmaoracle.com
Requires-Python: >=3.9,<3.10
Classifier: License :: OSI Approved :: MIT License
Classifier: Operating System :: OS Independent
Classifier: Programming Language :: Python :: 3
Classifier: Programming Language :: Python :: 3.9
Requires-Dist: cairo-lang (>=0.12,<0.13)
Requires-Dist: starknet.py (==0.18.1)
Requires-Dist: typer (==0.6.1)
Project-URL: Documentation, https://docs.pragmaoracle.com
Project-URL: Repository, https://github.com/Astraly-Labs/Pragma
